env_flag/__init__.py
env_flag/py.typed
env_flag-2.1.0.dist-info/LICENSE
env_flag-2.1.0.dist-info/METADATA
env_flag-2.1.0.dist-info/WHEEL
env_flag-2.1.0.dist-info/top_level.txt
env_flag-2.1.0.dist-info/RECORD
