Metadata-Version: 2.1
Name: env-flag
Version: 2.1.0
Summary: Get boolean values from environment variables
Home-page: https://github.com/metabolize/env-flag
Author: Body Labs & Metabolize
Author-email: github@paulmelnikow.com
License: BSD-2-Clause
Platform: UNKNOWN
Classifier: Development Status :: 5 - Production/Stable
Classifier: Intended Audience :: Developers
Classifier: License :: OSI Approved :: BSD License
Classifier: Operating System :: OS Independent
Classifier: Programming Language :: Python :: 3
